<?xml version="1.0" encoding="utf-8"?>
<!DOCTYPE hibernate-mapping PUBLIC "-//Hibernate/Hibernate Mapping DTD 3.0//EN"
"http://www.hibernate.org/dtd/hibernate-mapping-3.0.dtd">
<!-- 
    Mapping file autogenerated by MyEclipse Persistence Tools
-->
<hibernate-mapping>
    <class name="com.yunhai.excel.orm.OriOpticalCableTermianl" table="ORI_OPTICAL_CABLE_TERMIANL" >
        <id name="oriOpticalCableTermianlId" type="java.lang.String">
            <column name="ORI_OPTICAL_CABLE_TERMIANL_ID" length="100" />
            <generator class="uuid.hex" />
        </id>
        <property name="globalName" type="java.lang.String">
            <column name="GLOBAL_NAME" />
        </property>
        <property name="name" type="java.lang.String">
            <column name="NAME" />
        </property>
        <property name="abbreviation" type="java.lang.String">
            <column name="ABBREVIATION" />
        </property>
        <property name="subordinateComputerRoom" type="java.lang.String">
            <column name="SUBORDINATE_COMPUTER_ROOM" />
        </property>
        <property name="erpAssetCoding" type="java.lang.String">
            <column name="ERP_ASSET_CODING" length="100" />
        </property>
        <property name="erpEquipmentAccountCoding" type="java.lang.String">
            <column name="ERP_EQUIPMENT_ACCOUNT_CODING" length="100" />
        </property>
        <property name="subordinateSite" type="java.lang.String">
            <column name="SUBORDINATE_SITE" />
        </property>
        <property name="subordinateSystem" type="java.lang.String">
            <column name="SUBORDINATE_SYSTEM" />
        </property>
        <property name="manufacturer" type="java.lang.String">
            <column name="MANUFACTURER" />
        </property>
        <property name="manufacturerEquipmentType" type="java.lang.String">
            <column name="MANUFACTURER_EQUIPMENT_TYPE" />
        </property>
        <property name="commissioningDate"	type="java.util.Date">
            <column name="COMMISSIONING_DATE"/>
        </property>
        <property name="workingState" type="java.lang.String">
            <column name="WORKING_STATE" />
        </property>
        <property name="jurisdictionRightOrg" type="java.lang.String">
            <column name="JURISDICTION_RIGHT_ORG" />
        </property>
        <property name="dataMaintenanceOrg" type="java.lang.String">
            <column name="DATA_MAINTENANCE_ORG" />
        </property>
        <property name="propertyRightsOrg" type="java.lang.String">
            <column name="PROPERTY_RIGHTS_ORG" />
        </property>
        <property name="statisticalOrg" type="java.lang.String">
            <column name="STATISTICAL_ORG" />
        </property>
        <property name="defender" type="java.lang.String">
            <column name="DEFENDER" />
        </property>
        <property name="warningSurveillanceOrg" type="java.lang.String">
            <column name="WARNING_SURVEILLANCE_ORG" />
        </property>
        <property name="technicalSystem" type="java.lang.String">
            <column name="TECHNICAL_SYSTEM" />
        </property>
        <property name="equipmentType" type="java.lang.String">
            <column name="EQUIPMENT_TYPE" />
        </property>
        <property name="maximumCapacity" type="java.lang.String">
            <column name="MAXIMUM_CAPACITY" />
        </property>
        <property name="actualConfigurationMaxRate" type="java.lang.String">
            <column name="ACTUAL_CONFIGURATION_MAX_RATE" />
        </property>
        <property name="transportNetworkElementType" type="java.lang.String">
            <column name="TRANSPORT_NETWORK_ELEMENT_TYPE" />
        </property>
        <property name="dataVersion" type="java.lang.String">
            <column name="DATA_VERSION" />
        </property>
        <property name="dataSourceFile" type="java.lang.String">
            <column name="DATA_SOURCE_FILE" />
        </property>
    </class>
</hibernate-mapping>
