<?xml version="1.0" encoding="utf-8"?>
<!DOCTYPE hibernate-mapping PUBLIC "-//Hibernate/Hibernate Mapping DTD 3.0//EN"
"http://www.hibernate.org/dtd/hibernate-mapping-3.0.dtd">
<!-- 
    Mapping file autogenerated by MyEclipse Persistence Tools
-->
<hibernate-mapping>
    <class name="com.yunhai.excel.orm.OriWorkTaskInvoice" table="ORI_WORK_TASK_INVOICE">
        <id name="oriWorkTaskInvoiceId" type="java.lang.String">
            <column name="ORI_WORK_TASK_INVOICE_ID" length="100" />
            <generator class="uuid.hex" />
        </id>
        <property name="dataVersion" type="java.lang.String">
            <column name="DATA_VERSION" length="100" not-null="true" />
        </property>
        <property name="calYear" type="java.util.Date">
            <column name="CAL_YEAR" length="7" />
        </property>
        <property name="dataFile" type="java.lang.String">
            <column name="DATA_FILE" length="200" not-null="true" />
        </property>
        <property name="objId" type="java.lang.String">
            <column name="OBJ_ID" length="100" />
        </property>
        <property name="taskInvoiceName" type="java.lang.String">
            <column name="TASK_INVOICE_NAME" />
        </property>
        <property name="preparationDate" type="java.util.Date">
            <column name="PREPARATION_DATE" length="7" />
        </property>
        <property name="taskContent" type="java.lang.String">
            <column name="TASK_CONTENT" />
        </property>
        <property name="powerStationLine" type="java.lang.String">
            <column name="POWER_STATION_LINE" />
        </property>
        <property name="plannedStartTime" type="java.util.Date">
            <column name="PLANNED_START_TIME" length="7" />
        </property>
        <property name="plannedEndTime" type="java.util.Date">
            <column name="PLANNED_END_TIME" length="7" />
        </property>
        <property name="isPowerFailure" type="java.lang.String">
            <column name="IS_POWER_FAILURE" />
        </property>
        <property name="approvedOutageStartTime" type="java.lang.String">
            <column name="APPROVED_OUTAGE_START_TIME" />
        </property>
        <property name="approvedOutageEndTime" type="java.lang.String">
            <column name="APPROVED_OUTAGE_END_TIME" />
        </property>
        <property name="powerCutScope" type="java.lang.String">
            <column name="POWER_CUT_SCOPE" />
        </property>
        <property name="taskArrangerName" type="java.lang.String">
            <column name="TASK_ARRANGER_NAME" />
        </property>
        <property name="completionPhase" type="java.lang.String">
            <column name="COMPLETION_PHASE" />
        </property>
        <property name="major" type="java.lang.String">
            <column name="MAJOR" />
        </property>
        <property name="belongedCityName" type="java.lang.String">
            <column name="BELONGED_CITY_NAME" />
        </property>
        <property name="preparationDepartmentName" type="java.lang.String">
            <column name="PREPARATION_DEPARTMENT_NAME" />
        </property>
        <property name="stationLineType" type="java.lang.String">
            <column name="STATION_LINE_TYPE" />
        </property>
        <property name="whetherAllocateOtherOrg" type="java.lang.String">
            <column name="WHETHER_ALLOCATE_OTHER_ORG" />
        </property>
        <property name="responsibleOrg" type="java.lang.String">
            <column name="RESPONSIBLE_ORG" />
        </property>
    </class>
</hibernate-mapping>
