<?xml version="1.0" encoding="utf-8"?>
<!DOCTYPE hibernate-mapping PUBLIC "-//Hibernate/Hibernate Mapping DTD 3.0//EN"
"http://www.hibernate.org/dtd/hibernate-mapping-3.0.dtd">
<!-- 
    Mapping file autogenerated by MyEclipse Persistence Tools
-->
<hibernate-mapping>
    <class name="com.yunhai.excel.orm.ZfiSwzcNo16classValue" table="ZFI_SWZC_NO16CLASS_VALUE" schema="ZCFX_NEW">
        <id name="zfiSwzc16classValueId" type="java.lang.String">
            <column name="ZFI_SWZC_16CLASS_VALUE_ID" length="50" />
			<generator class="uuid.hex" />
        </id>
        <property name="dataVersion" type="java.lang.String">
            <column name="DATA_VERSION" length="50" />
        </property>
        <property name="calYear" type="java.util.Date">
            <column name="CAL_YEAR" length="7" />
        </property>
        <property name="assetMain" type="java.lang.String">
            <column name="ASSET_MAIN" length="50" />
        </property>
        <property name="equnr" type="java.lang.String">
            <column name="EQUNR" length="50" />
        </property>
        <property name="zpmzcyz" type="java.lang.Double">
            <column name="ZPMZCYZ" precision="17" scale="3" />
        </property>
        <property name="zpmzcjz" type="java.lang.Double">
            <column name="ZPMZCJZ" precision="17" scale="3" />
        </property>
        <property name="dataSourceFile" type="java.lang.String">
            <column name="DATA_SOURCE_FILE" />
        </property>
    </class>
</hibernate-mapping>
